LICENSE.txt
README.md
setup.py
sqlalchemy_counter/__init__.py
sqlalchemy_counter/sqlalchemy_counter.py
sqlalchemy_counter.egg-info/PKG-INFO
sqlalchemy_counter.egg-info/SOURCES.txt
sqlalchemy_counter.egg-info/dependency_links.txt
sqlalchemy_counter.egg-info/requires.txt
sqlalchemy_counter.egg-info/top_level.txt